aerocm/.ipynb_checkpoints/example_climate_metrics-checkpoint.ipynb
aerocm/.ipynb_checkpoints/example_climate_simulation-checkpoint.ipynb
aerocm/__init__.py
aerocm/climate_data/aviation_emissions_data.csv
aerocm/climate_data/concentration/concentration_data.csv
aerocm/climate_data/dallara_data.csv
aerocm/climate_data/erf_nox_lee.csv
aerocm/climate_data/historical_data_from_klower.csv
aerocm/climate_data/RCP/RCP26.csv
aerocm/climate_data/RCP/RCP45.csv
aerocm/climate_data/RCP/RCP60.csv
aerocm/climate_data/RCP/RCP85.csv
aerocm/climate_data/reference_temperature_change_historic.csv
aerocm/climate_data/temperature_historical_dataset.csv
aerocm/climate_models/__init__.py
aerocm/climate_models/aviation_climate_simulation.py
aerocm/climate_models/fair_climate_model.py
aerocm/climate_models/gwpstar_climate_model.py
aerocm/climate_models/ipcc_climate_model.py
aerocm/climate_models/lwe_climate_model.py
aerocm/climate_models/template.py
aerocm/metrics/__init__.py
aerocm/metrics/aviation_climate_metrics_calculation.py
aerocm/metrics/metrics.py
aerocm/notebooks/.ipynb_checkpoints/example_climate_metrics-checkpoint.ipynb
aerocm/notebooks/.ipynb_checkpoints/example_climate_simulation-checkpoint.ipynb
aerocm/notebooks/example_climate_metrics.ipynb
aerocm/notebooks/example_climate_simulation.ipynb
aerocm/publications/.ipynb_checkpoints/alternative_settings-checkpoint.ipynb
aerocm/publications/.ipynb_checkpoints/altitude_effect-checkpoint.ipynb
aerocm/publications/.ipynb_checkpoints/climate_models_comparison-checkpoint.ipynb
aerocm/publications/.ipynb_checkpoints/metrics_pulse_sensitivity-checkpoint.ipynb
aerocm/publications/.ipynb_checkpoints/metrics_time_horizon_sensitivity-checkpoint.ipynb
aerocm/publications/.ipynb_checkpoints/regional_effect-checkpoint.ipynb
aerocm/publications/.ipynb_checkpoints/route_contrails-checkpoint.ipynb
aerocm/publications/.ipynb_checkpoints/sensitivity_to_scenarios-checkpoint.ipynb
aerocm/publications/.ipynb_checkpoints/surrogate_models-checkpoint.ipynb
aerocm-0.1.0b0.dist-info/licenses/COPYING
aerocm-0.1.0b0.dist-info/METADATA
aerocm-0.1.0b0.dist-info/WHEEL
aerocm-0.1.0b0.dist-info/RECORD
