Metadata-Version: 2.4
Name: aerocm
Version: 0.1.0b0
Summary: AeroCM: standardised climate models dedicated to aviation
License: GPL-3.0-only
License-File: COPYING
Author: Thomas PLANES
Author-email: thomas.planes@isae-supaero.fr
Requires-Python: >=3.10,<3.12
Classifier: License :: OSI Approved :: GNU General Public License v3 (GPLv3)
Classifier: Programming Language :: Python :: 3
Classifier: Programming Language :: Python :: 3.10
Classifier: Programming Language :: Python :: 3.11
Provides-Extra: publications
Requires-Dist: cartopy (==0.25.0) ; extra == "publications"
Requires-Dist: fair (==2.2.2)
Requires-Dist: geographiclib (==2.1) ; extra == "publications"
Requires-Dist: ipympl (==0.9.7)
Requires-Dist: jupyterlab (==4.4.9)
Requires-Dist: netCDF4 (==1.7.2) ; extra == "publications"
Requires-Dist: numpy (==2.2.6)
Requires-Dist: openpyxl (==3.1.5) ; extra == "publications"
Requires-Dist: pandas (==2.3.3)
Requires-Dist: salib (==1.5.1) ; extra == "publications"
Requires-Dist: scikit-learn (==1.7.2) ; extra == "publications"
Requires-Dist: scipy (==1.15.3) ; extra == "publications"
Requires-Dist: seaborn (==0.13.2) ; extra == "publications"
Requires-Dist: xarray (==2025.6.1)
